colorama_terminal/__init__.py
colorama_terminal-0.0.1.dist-info/LICENSE
colorama_terminal-0.0.1.dist-info/METADATA
colorama_terminal-0.0.1.dist-info/WHEEL
colorama_terminal-0.0.1.dist-info/top_level.txt
colorama_terminal-0.0.1.dist-info/RECORD
