Metadata-Version: 2.1
Name: colorama-terminal
Version: 0.0.1
Summary: 在终端有颜色地打印python变量
Home-page: https://github.com/nanarino/colorama-terminal
Classifier: Programming Language :: Python :: 3
Classifier: License :: OSI Approved :: MIT License
Classifier: Operating System :: OS Independent
Requires-Python: >=3.6
License-File: LICENSE
